{"assets":{"710FDE7CCC8D3154692558D15C311174":{"type":"texture","index":0,"assetRequest":{"type":"slide","state":"contents","slide":"none"},"url":{"native":"assets\/4250E602-491B-429B-A360-66C3981AAE74.pdf"},"width":720,"height":405},"DC2F621CA133FDDFECEA5B5C3E540E18":{"type":"texture","index":1,"assetRequest":{"type":"slide","state":"contents","slide":"none"},"url":{"native":"assets\/4250E602-491B-429B-A360-66C3981AAE74.pdf"},"width":720,"height":405},"CE4887950F8AA91F08AD3C2AF5EB08A2":{"type":"texture","index":2,"assetRequest":{"type":"slide","state":"contents","slide":"none"},"url":{"native":"assets\/4250E602-491B-429B-A360-66C3981AAE74.pdf"},"width":720,"height":405}},"events":[{"effects":[{"beginTime":0,"baseLayer":{"animations":[],"initialState":{"affineTransform":[1,0,0,1,0,0],"masksToBounds":false,"rotation":0,"scale":1,"position":{"pointX":360,"pointY":202.5},"width":720,"sublayerTransform":[1,0,0,0,0,1,0,0,0,0,1,0,0,0,0,1],"contentsRect":{"y":0,"x":0,"width":1,"height":1},"opacity":1,"edgeAntialiasingMask":251658240,"height":405,"hidden":false,"anchorPoint":{"pointX":0.5,"pointY":0.5}},"objectID":"0","layers":[{"animations":[],"initialState":{"affineTransform":[1,0,0,1,0,0],"masksToBounds":false,"rotation":0,"scale":1,"position":{"pointX":360,"pointY":202.5},"width":720,"sublayerTransform":[1,0,0,0,0,1,0,0,0,0,1,-0.00093354433244735948,0,0,0,1],"contentsRect":{"y":0,"x":0,"width":1,"height":1},"opacity":1,"edgeAntialiasingMask":251658240,"height":405,"hidden":false,"anchorPoint":{"pointX":0.5,"pointY":0.5}},"layers":[{"animations":[],"layers":[],"texturedRectangle":{"isBackgroundTexture":false,"singleTextureOpacity":1,"textureType":0,"textBaseline":0,"textXHeight":0,"isVerticalText":false},"initialState":{"affineTransform":[1,0,0,1,0,0],"masksToBounds":false,"rotation":0,"scale":1,"position":{"pointX":360,"pointY":202.5},"width":720,"sublayerTransform":[1,0,0,0,0,1,0,0,0,0,1,0,0,0,0,1],"contentsRect":{"y":0,"x":0,"width":1,"height":1},"opacity":1,"edgeAntialiasingMask":0,"height":405,"hidden":false,"anchorPoint":{"pointX":0.5,"pointY":0.5}},"texture":"DC2F621CA133FDDFECEA5B5C3E540E18"},{"animations":[{"timeOffset":0,"from":{"scalar":false},"beginTime":0,"repeatCount":0,"fillMode":"both","property":"hidden","autoreverses":false,"duration":0.01,"to":{"scalar":true}}],"layers":[],"texturedRectangle":{"isBackgroundTexture":false,"singleTextureOpacity":1,"textureType":0,"textBaseline":0,"textXHeight":0,"isVerticalText":false},"initialState":{"affineTransform":[1,0,0,1,0,0],"masksToBounds":false,"rotation":0,"scale":1,"position":{"pointX":360,"pointY":202.5},"width":720,"sublayerTransform":[1,0,0,0,0,1,0,0,0,0,1,0,0,0,0,1],"contentsRect":{"y":0,"x":0,"width":1,"height":1},"opacity":1,"edgeAntialiasingMask":0,"height":405,"hidden":false,"anchorPoint":{"pointX":0.5,"pointY":0.5}},"texture":"710FDE7CCC8D3154692558D15C311174"}]}]},"effects":[],"duration":0.01,"type":"transition","name":"none","objectID":"0"}],"automaticPlay":false,"hyperlinks":[{"url":"?slideid=F1A411D8-67DE-44C2-A019-70D1F9A26ACE","events":{"F1A411D8-67DE-44C2-A019-70D1F9A26ACE":{"effects":[{"beginTime":0,"baseLayer":{"animations":[],"initialState":{"affineTransform":[1,0,0,1,0,0],"masksToBounds":false,"rotation":0,"scale":1,"position":{"pointX":360,"pointY":202.5},"width":720,"sublayerTransform":[1,0,0,0,0,1,0,0,0,0,1,0,0,0,0,1],"contentsRect":{"y":0,"x":0,"width":1,"height":1},"opacity":1,"edgeAntialiasingMask":251658240,"height":405,"hidden":false,"anchorPoint":{"pointX":0.5,"pointY":0.5}},"objectID":"0","layers":[{"animations":[],"initialState":{"affineTransform":[1,0,0,1,0,0],"masksToBounds":false,"rotation":0,"scale":1,"position":{"pointX":360,"pointY":202.5},"width":720,"sublayerTransform":[1,0,0,0,0,1,0,0,0,0,1,-0.00093354433244735948,0,0,0,1],"contentsRect":{"y":0,"x":0,"width":1,"height":1},"opacity":1,"edgeAntialiasingMask":251658240,"height":405,"hidden":false,"anchorPoint":{"pointX":0.5,"pointY":0.5}},"layers":[{"animations":[],"layers":[],"texturedRectangle":{"isBackgroundTexture":false,"singleTextureOpacity":1,"textureType":0,"textBaseline":0,"textXHeight":0,"isVerticalText":false},"initialState":{"affineTransform":[1,0,0,1,0,0],"masksToBounds":false,"rotation":0,"scale":1,"position":{"pointX":360,"pointY":202.5},"width":720,"sublayerTransform":[1,0,0,0,0,1,0,0,0,0,1,0,0,0,0,1],"contentsRect":{"y":0,"x":0,"width":1,"height":1},"opacity":1,"edgeAntialiasingMask":0,"height":405,"hidden":false,"anchorPoint":{"pointX":0.5,"pointY":0.5}},"texture":"CE4887950F8AA91F08AD3C2AF5EB08A2"},{"animations":[{"timeOffset":0,"from":{"scalar":false},"beginTime":0,"repeatCount":0,"fillMode":"both","property":"hidden","autoreverses":false,"duration":0.01,"to":{"scalar":true}}],"layers":[],"texturedRectangle":{"isBackgroundTexture":false,"singleTextureOpacity":1,"textureType":0,"textBaseline":0,"textXHeight":0,"isVerticalText":false},"initialState":{"affineTransform":[1,0,0,1,0,0],"masksToBounds":false,"rotation":0,"scale":1,"position":{"pointX":360,"pointY":202.5},"width":720,"sublayerTransform":[1,0,0,0,0,1,0,0,0,0,1,0,0,0,0,1],"contentsRect":{"y":0,"x":0,"width":1,"height":1},"opacity":1,"edgeAntialiasingMask":0,"height":405,"hidden":false,"anchorPoint":{"pointX":0.5,"pointY":0.5}},"texture":"710FDE7CCC8D3154692558D15C311174"}]}]},"effects":[],"duration":0.01,"type":"transition","name":"none","objectID":"0"}],"automaticPlay":false,"hyperlinks":[],"accessibility":[],"baseLayer":{"animations":[],"initialState":{"affineTransform":[1,0,0,1,0,0],"masksToBounds":false,"rotation":0,"scale":1,"position":{"pointX":360,"pointY":202.5},"width":720,"sublayerTransform":[1,0,0,0,0,1,0,0,0,0,1,0,0,0,0,1],"contentsRect":{"y":0,"x":0,"width":1,"height":1},"opacity":1,"edgeAntialiasingMask":251658240,"height":405,"hidden":false,"anchorPoint":{"pointX":0.5,"pointY":0.5}},"objectID":"0","layers":[{"animations":[],"initialState":{"affineTransform":[1,0,0,1,0,0],"masksToBounds":false,"rotation":0,"scale":1,"position":{"pointX":360,"pointY":202.5},"width":720,"sublayerTransform":[1,0,0,0,0,1,0,0,0,0,1,-0.00093354433244735948,0,0,0,1],"contentsRect":{"y":0,"x":0,"width":1,"height":1},"opacity":1,"edgeAntialiasingMask":251658240,"height":405,"hidden":false,"anchorPoint":{"pointX":0.5,"pointY":0.5}},"layers":[{"animations":[],"layers":[],"texturedRectangle":{"isBackgroundTexture":false,"singleTextureOpacity":1,"textureType":0,"textBaseline":0,"textXHeight":0,"isVerticalText":false},"initialState":{"affineTransform":[1,0,0,1,0,0],"masksToBounds":false,"rotation":0,"scale":1,"position":{"pointX":360,"pointY":202.5},"width":720,"sublayerTransform":[1,0,0,0,0,1,0,0,0,0,1,0,0,0,0,1],"contentsRect":{"y":0,"x":0,"width":1,"height":1},"opacity":1,"edgeAntialiasingMask":0,"height":405,"hidden":false,"anchorPoint":{"pointX":0.5,"pointY":0.5}},"texture":"710FDE7CCC8D3154692558D15C311174"}]}]}}},"targetRectangle":{"y":309.92738624408344,"x":647.12502064078103,"width":40.080709241767181,"height":34.79087414692799}}],"accessibility":[{"text":"FICHA TÉCNICA:","targetRectangle":{"y":66.20471722685437,"x":153.04598734697953,"width":88.8056640625,"height":13.386156949040014}},{"text":"PESO: Podem pesar até 200 Kg.","targetRectangle":{"y":79.950737457144385,"x":55.190942505213172,"width":161.42822265625,"height":19.386156949040014}},{"text":"COMPRIMENTO: Algumas com 2 centímetros e outras  com até 2 metros de diâmetro com tentáculos até 40 metros de comprimento.","targetRectangle":{"y":99.696757687434399,"x":55.190942505213172,"width":284.51575374603294,"height":46.878197409620043}},{"text":"ONDE VIVE: Mares Tropicais e nas águas frias do Ártico.","targetRectangle":{"y":146.93481837830444,"x":55.190942505213172,"width":280.00048828125,"height":19.386156949040014}},{"text":"ALIMENTAÇÃO: Algas, crustáceos e outros animais aquáticos.","targetRectangle":{"y":166.68083860859446,"x":55.190942505213172,"width":284.51575374603266,"height":33.132177179330029}},{"text":"CURIOSIDADES: A maioria é transparente e tem o formato de um sino. A boca fica no centro do corpo.","targetRectangle":{"y":200.17287906917448,"x":55.190942505213172,"width":284.51575374603283,"height":33.132177179330029}},{"text":"ESCRITO POR: David Miguel Oliveira de Santana e Manuela Andrello Ceregatti.","targetRectangle":{"y":253.41093976004453,"x":55.190942505213172,"width":284.51575374603277,"height":33.132177179330029}},{"text":"RETORNAR","targetRectangle":{"y":317.54922174093292,"x":548.93831748662035,"width":89.3359375,"height":23}},{"text":"Google Shape;142;p20","targetRectangle":{"y":73.270706176757812,"x":394.88290405273438,"width":218.49015808105469,"height":145.62400817871094}}],"baseLayer":{"animations":[],"initialState":{"affineTransform":[1,0,0,1,0,0],"masksToBounds":false,"rotation":0,"scale":1,"position":{"pointX":360,"pointY":202.5},"width":720,"sublayerTransform":[1,0,0,0,0,1,0,0,0,0,1,0,0,0,0,1],"contentsRect":{"y":0,"x":0,"width":1,"height":1},"opacity":1,"edgeAntialiasingMask":251658240,"height":405,"hidden":false,"anchorPoint":{"pointX":0.5,"pointY":0.5}},"objectID":"0","layers":[{"animations":[],"initialState":{"affineTransform":[1,0,0,1,0,0],"masksToBounds":false,"rotation":0,"scale":1,"position":{"pointX":360,"pointY":202.5},"width":720,"sublayerTransform":[1,0,0,0,0,1,0,0,0,0,1,-0.00093354433244735948,0,0,0,1],"contentsRect":{"y":0,"x":0,"width":1,"height":1},"opacity":1,"edgeAntialiasingMask":251658240,"height":405,"hidden":false,"anchorPoint":{"pointX":0.5,"pointY":0.5}},"layers":[{"animations":[],"layers":[],"texturedRectangle":{"isBackgroundTexture":false,"singleTextureOpacity":1,"textureType":0,"textBaseline":0,"textXHeight":0,"isVerticalText":false},"initialState":{"affineTransform":[1,0,0,1,0,0],"masksToBounds":false,"rotation":0,"scale":1,"position":{"pointX":360,"pointY":202.5},"width":720,"sublayerTransform":[1,0,0,0,0,1,0,0,0,0,1,0,0,0,0,1],"contentsRect":{"y":0,"x":0,"width":1,"height":1},"opacity":1,"edgeAntialiasingMask":0,"height":405,"hidden":false,"anchorPoint":{"pointX":0.5,"pointY":0.5}},"texture":"710FDE7CCC8D3154692558D15C311174"}]}]}}]}